aiobosest/__init__.py
aiobosest/aiobosest.py
aiobosest/connection.py
aiobosest/errors.py
aiobosest/log.py
aiobosest/utils.py
aiobosest/helpers/__init__.py
aiobosest/helpers/base.py
aiobosest/helpers/key.py
aiobosest/helpers/now_playing.py
aiobosest/helpers/presets.py
aiobosest/helpers/sources.py
aiobosest/helpers/volume.py
aiobosest-0.0.4.dist-info/DESCRIPTION.rst
aiobosest-0.0.4.dist-info/METADATA
aiobosest-0.0.4.dist-info/RECORD
aiobosest-0.0.4.dist-info/WHEEL
aiobosest-0.0.4.dist-info/metadata.json
aiobosest-0.0.4.dist-info/top_level.txt
