Metadata-Version: 2.0
Name: aiobosest
Version: 0.0.4
Summary: Asynchronous python wrapper to Bose SoundTouch API
Home-page: https://github.com/trunet/aiobosest
Author: Wagner Sartori Junior
Author-email: wsartori@wsartori.com
License: GPLv3
Download-URL: https://github.com/trunet/aiobosest
Platform: UNKNOWN
Classifier: Development Status :: 4 - Beta
Classifier: Programming Language :: Python :: 3.5
Classifier: Topic :: Home Automation
Classifier: Topic :: Multimedia :: Sound/Audio
Classifier: Topic :: Software Development :: Libraries :: Python Modules
Classifier: License :: OSI Approved :: GNU General Public License v3 (GPLv3)
Requires-Dist: aiohttp (>=1.1.4)
Requires-Dist: lxml (>=3.6.4)
Requires-Dist: zeroconf (>=0.17.6)
